synctera_client/__init__.py
synctera_client/api_client.py
synctera_client/apis/__init__.py
synctera_client/apis/path_to_api.py
synctera_client/apis/paths/__init__.py
synctera_client/apis/paths/accounts.py
synctera_client/apis/paths/accounts_account_id.py
synctera_client/apis/paths/accounts_account_id_relationships.py
synctera_client/apis/paths/accounts_account_id_relationships_relationship_id.py
synctera_client/apis/paths/accounts_products.py
synctera_client/apis/paths/accounts_products_product_id.py
synctera_client/apis/paths/accounts_templates.py
synctera_client/apis/paths/accounts_templates_template_id.py
synctera_client/apis/paths/ach.py
synctera_client/apis/paths/ach_transaction_id.py
synctera_client/apis/paths/ach_transaction_simulations_receiving_return.py
synctera_client/apis/paths/ach_transaction_simulations_receiving_transaction.py
synctera_client/apis/paths/businesses.py
synctera_client/apis/paths/businesses_business_id.py
synctera_client/apis/paths/cards.py
synctera_client/apis/paths/cards_activate.py
synctera_client/apis/paths/cards_card_id.py
synctera_client/apis/paths/cards_card_id_barcodes.py
synctera_client/apis/paths/cards_card_id_changes.py
synctera_client/apis/paths/cards_card_id_client_token.py
synctera_client/apis/paths/cards_card_id_digital_wallet_tokens_applepay.py
synctera_client/apis/paths/cards_card_id_digital_wallet_tokens_googlepay.py
synctera_client/apis/paths/cards_card_id_webhook_simulations_fulfillment.py
synctera_client/apis/paths/cards_card_widget_url.py
synctera_client/apis/paths/cards_digital_wallet_tokens.py
synctera_client/apis/paths/cards_digital_wallet_tokens_digital_wallet_token_id.py
synctera_client/apis/paths/cards_gateways.py
synctera_client/apis/paths/cards_gateways_gateway_id.py
synctera_client/apis/paths/cards_images.py
synctera_client/apis/paths/cards_images_card_image_id.py
synctera_client/apis/paths/cards_images_card_image_id_data.py
synctera_client/apis/paths/cards_products.py
synctera_client-0.49.0.dist-info/METADATA
synctera_client-0.49.0.dist-info/WHEEL
synctera_client-0.49.0.dist-info/RECORD
