Metadata-Version: 2.1
Name: synctera-client
Version: 0.49.0
Summary: Synctera API Client generated by openapi-generator
Author: Swadesh
Author-email: dev@swadesh.co
Maintainer: D. Kasi Pavan Kumar
Maintainer-email: kasi@swadesh.co
Requires-Python: >=3.7,<4.0
Classifier: Programming Language :: Python :: 3
Classifier: Programming Language :: Python :: 3.7
Classifier: Programming Language :: Python :: 3.8
Classifier: Programming Language :: Python :: 3.9
Classifier: Programming Language :: Python :: 3.10
Classifier: Programming Language :: Python :: 3.11
Requires-Dist: certifi (>=2017.4.17,<2018.0.0)
Requires-Dist: frozendict (>=2.3.4,<3.0.0)
Requires-Dist: python-dateutil (>=2.7.0,<3.0.0)
Requires-Dist: typing_extensions (>=4.3.0,<5.0.0)
Requires-Dist: urllib3 (>=1.26.7,<2.0.0)
